knosk/__init__.py
knosk/choosers/__init__.py
knosk/choosers/chooser.py
knosk/core/__init__.py
knosk/core/dialogform.py
knosk/core/flowmanager.py
knosk/core/historymanager.py
knosk/core/messages.py
knosk/core/render.py
knosk/core/serializer.py
knosk/fields/__init__.py
knosk/fields/dialogfield.py
knosk/fields/dialogfieldvalue.py
knosk/matchers/__init__.py
knosk/matchers/matcher.py
knosk/suggesters/__init__.py
knosk/suggesters/suggester.py
knosk_core-1.0.0a1.dist-info/LICENSE
knosk_core-1.0.0a1.dist-info/METADATA
knosk_core-1.0.0a1.dist-info/WHEEL
knosk_core-1.0.0a1.dist-info/top_level.txt
knosk_core-1.0.0a1.dist-info/RECORD
