Metadata-Version: 2.1
Name: knosk-core
Version: 1.0.0a1
Summary: Knosk dialog management framework
Home-page: https://github.com/knosk/knosk-core
Author: Knosk team
Author-email: info@knosk.com
License: MIT
Platform: Posix; MacOS X
Classifier: Development Status :: 1 - Planning
Classifier: Intended Audience :: Developers
Classifier: License :: OSI Approved :: MIT License
Classifier: Operating System :: POSIX
Classifier: Topic :: Communications :: Chat
Classifier: Topic :: Text Processing :: Linguistic
Classifier: Programming Language :: Python :: 3
Classifier: Programming Language :: Python :: 3.6
Classifier: Programming Language :: Python :: 3.7
Requires-Python: >=3.6
Requires-Dist: jinja2
Requires-Dist: python-dateutil
